gumicorn/__init__.py
gumicorn/__main__.py
gumicorn/arbiter.py
gumicorn/config.py
gumicorn/debug.py
gumicorn/errors.py
gumicorn/glogging.py
gumicorn/pidfile.py
gumicorn/reloader.py
gumicorn/sock.py
gumicorn/util.py
gumicorn/app/__init__.py
gumicorn/app/base.py
gumicorn/app/pasterapp.py
gumicorn/app/wsgiapp.py
gumicorn/http/__init__.py
gumicorn/http/body.py
gumicorn/http/errors.py
gumicorn/http/message.py
gumicorn/http/parser.py
gumicorn/http/unreader.py
gumicorn/http/wsgi.py
gumicorn/instrument/__init__.py
gumicorn/instrument/statsd.py
gumicorn/workers/__init__.py
gumicorn/workers/base.py
gumicorn/workers/base_async.py
gumicorn/workers/geventlet.py
gumicorn/workers/ggevent.py
gumicorn/workers/gthread.py
gumicorn/workers/gtornado.py
gumicorn/workers/sync.py
gumicorn/workers/workertmp.py
gumicorn-23.0.4.dist-info/licenses/LICENSE
gumicorn-23.0.4.dist-info/METADATA
gumicorn-23.0.4.dist-info/WHEEL
gumicorn-23.0.4.dist-info/entry_points.txt
gumicorn-23.0.4.dist-info/top_level.txt
gumicorn-23.0.4.dist-info/RECORD
